perfcounters/__init__.py
perfcounters/format.py
perfcounters/time_counters.py
perfcounters/value_counters.py
perfcounters-3.0.1.dist-info/LICENSE
perfcounters-3.0.1.dist-info/METADATA
perfcounters-3.0.1.dist-info/WHEEL
perfcounters-3.0.1.dist-info/top_level.txt
perfcounters-3.0.1.dist-info/RECORD
