Metadata-Version: 2.1
Name: perfcounters
Version: 3.0.1
Summary: Easily add performance counters to your code
Home-page: https://github.com/ebursztein/perfcounters
Author: Elie Bursztein
Author-email: code@elie.net
License: Apache 2
Classifier: Development Status :: 5 - Production/Stable
Classifier: Intended Audience :: Developers
Classifier: Intended Audience :: Education
Classifier: Intended Audience :: Science/Research
Classifier: License :: OSI Approved :: Apache Software License
Classifier: Programming Language :: Python :: 3
Classifier: Topic :: Software Development :: Libraries
Classifier: Topic :: Software Development :: Libraries :: Python Modules
Classifier: Topic :: Software Development :: Debuggers
Classifier: Topic :: Software Development :: Testing
License-File: LICENSE
Requires-Dist: tabulate
